gdschamfer/__init__.py
gdschamfer/_static_version.py
gdschamfer/_version.py
gdschamfer/gdschamfer.py
gdschamfer-0.3.0.dist-info/LICENSE
gdschamfer-0.3.0.dist-info/METADATA
gdschamfer-0.3.0.dist-info/WHEEL
gdschamfer-0.3.0.dist-info/top_level.txt
gdschamfer-0.3.0.dist-info/RECORD
