Metadata-Version: 2.1
Name: gdschamfer
Version: 0.3.0
Summary: Python add-on module for gdspy that can perform chamfering operation on GDSII files.
Home-page: https://github.com/arun-goud/gdschamfer
Author: arun-goud
Author-email: 72409952+arun-goud@users.noreply.github.com
License: Boost Software License - Version 1.0
Platform: UNKNOWN
Classifier: Development Status :: 5 - Production/Stable
Classifier: Environment :: Console
Classifier: Intended Audience :: Developers
Classifier: Intended Audience :: Manufacturing
Classifier: Intended Audience :: Science/Research
Classifier: License :: OSI Approved :: Boost Software License 1.0 (BSL-1.0)
Classifier: Operating System :: OS Independent
Classifier: Programming Language :: Python
Classifier: Topic :: Scientific/Engineering :: Electronic Design Automation (EDA)
Requires-Python: >=3.8
Requires-Dist: gdspy
